MANIFEST.in
requirements.txt
setup.py
rqalpha_mod_event_queue/__init__.py
rqalpha_mod_event_queue/__init__.pyc
rqalpha_mod_event_queue/mod.py
rqalpha_mod_event_queue/mod.pyc
rqalpha_mod_event_queue/queued_event_bus.py
rqalpha_mod_event_queue/queued_event_bus.pyc
rqalpha_mod_event_queue.egg-info/PKG-INFO
rqalpha_mod_event_queue.egg-info/SOURCES.txt
rqalpha_mod_event_queue.egg-info/dependency_links.txt
rqalpha_mod_event_queue.egg-info/not-zip-safe
rqalpha_mod_event_queue.egg-info/requires.txt
rqalpha_mod_event_queue.egg-info/top_level.txt