Metadata-Version: 1.1
Name: rqalpha-mod-event-queue
Version: 0.0.5
Summary: A mod for RQAlpha to replace its default event bus with a queued event bus.
Home-page: UNKNOWN
Author: cuizi7
Author-email: cuizi7@163.com
License: Apache License v2
Platform: UNKNOWN
Classifier: Programming Language :: Python
Classifier: Operating System :: Microsoft :: Windows
Classifier: Operating System :: Unix
Classifier: Programming Language :: Python :: 2.7
Classifier: Programming Language :: Python :: 3.4
Classifier: Programming Language :: Python :: 3.5
Classifier: Programming Language :: Python :: 3.6
